satosa/__init__.py
satosa/attribute_mapping.py
satosa/base.py
satosa/context.py
satosa/cookies.py
satosa/exception.py
satosa/internal.py
satosa/logging_util.py
satosa/plugin_loader.py
satosa/proxy_server.py
satosa/response.py
satosa/routing.py
satosa/saml_util.py
satosa/satosa_config.py
satosa/state.py
satosa/util.py
satosa/version.py
satosa/wsgi.py
satosa/yaml.py
satosa/backends/__init__.py
satosa/backends/apple.py
satosa/backends/base.py
satosa/backends/bitbucket.py
satosa/backends/github.py
satosa/backends/idpy_oidc.py
satosa/backends/linkedin.py
satosa/backends/oauth.py
satosa/backends/openid_connect.py
satosa/backends/orcid.py
satosa/backends/reflector.py
satosa/backends/saml2.py
satosa/frontends/__init__.py
satosa/frontends/base.py
satosa/frontends/openid_connect.py
satosa/frontends/ping.py
satosa/frontends/saml2.py
satosa/metadata_creation/__init__.py
satosa/metadata_creation/description.py
satosa/metadata_creation/saml_metadata.py
satosa/micro_services/__init__.py
satosa/micro_services/account_linking.py
satosa/micro_services/attribute_authorization.py
satosa/micro_services/attribute_generation.py
satosa/micro_services/attribute_modifications.py
satosa/micro_services/attribute_policy.py
satosa/micro_services/attribute_processor.py
satosa/micro_services/base.py
satosa/micro_services/consent.py
satosa/micro_services/custom_logging.py
satosa/micro_services/custom_routing.py
satosa/micro_services/disco.py
satosa/micro_services/hasher.py
satosa/micro_services/idp_hinting.py
satosa/micro_services/ldap_attribute_store.py
satosa/micro_services/primary_identifier.py
satosa/micro_services/processors/__init__.py
satosa/micro_services/processors/base_processor.py
satosa/micro_services/processors/gender_processor.py
satosa/micro_services/processors/hash_processor.py
satosa/micro_services/processors/regex_sub_processor.py
satosa/micro_services/processors/scope_extractor_processor.py
satosa/micro_services/processors/scope_processor.py
SATOSA-8.5.0.dist-info/LICENSE
SATOSA-8.5.0.dist-info/METADATA
SATOSA-8.5.0.dist-info/NOTICE
SATOSA-8.5.0.dist-info/WHEEL
SATOSA-8.5.0.dist-info/entry_points.txt
SATOSA-8.5.0.dist-info/top_level.txt
SATOSA-8.5.0.dist-info/RECORD
