Metadata-Version: 2.1
Name: SATOSA
Version: 8.5.0
Summary: Protocol proxy (SAML/OIDC).
Home-page: https://github.com/SUNET/SATOSA
Author: DIRG
Author-email: satosa-dev@lists.sunet.se
License: Apache 2.0
Classifier: Programming Language :: Python :: 3 :: Only
Classifier: Programming Language :: Python :: 3.6
Classifier: Programming Language :: Python :: 3.7
Classifier: Programming Language :: Python :: 3.8
Classifier: Programming Language :: Python :: 3.9
Classifier: Programming Language :: Python :: 3.10
Classifier: Programming Language :: Python :: 3.11
License-File: LICENSE
License-File: NOTICE
Requires-Dist: pyop (>=v3.4.0)
Requires-Dist: pysaml2 (>=6.5.1)
Requires-Dist: pycryptodomex
Requires-Dist: requests
Requires-Dist: PyYAML
Requires-Dist: gunicorn
Requires-Dist: Werkzeug
Requires-Dist: click
Requires-Dist: chevron
Requires-Dist: cookies-samesite-compat
Requires-Dist: importlib-metadata (>=1.7.0) ; python_version <= "3.8"
Provides-Extra: idpy_oidc_backend
Requires-Dist: idpyoidc (>=2.1.0) ; extra == 'idpy_oidc_backend'
Provides-Extra: ldap
Requires-Dist: ldap3 ; extra == 'ldap'
Provides-Extra: pyop_mongo
Requires-Dist: pyop[mongo] ; extra == 'pyop_mongo'
Provides-Extra: pyop_redis
Requires-Dist: pyop[redis] ; extra == 'pyop_redis'
